koalafix/Cell.py
koalafix/CellBase.py
koalafix/ExcelCompiler.py
koalafix/ExcelError.py
koalafix/Range.py
koalafix/Readme.md
koalafix/Spreadsheet.py
koalafix/__init__.py
koalafix/ast/__init__.py
koalafix/ast/astnodes.py
koalafix/excellib.py
koalafix/functions.json
koalafix/reader.py
koalafix/serializer.py
koalafix/tokenizer.py
koalafix/utils.py
koalafix-0.1.0.dist-info/LICENSE.txt
koalafix-0.1.0.dist-info/METADATA
koalafix-0.1.0.dist-info/WHEEL
koalafix-0.1.0.dist-info/RECORD
