Metadata-Version: 2.1
Name: koalafix
Version: 0.1.0
Summary: 
Author: drose15-chwy
Author-email: drose15@chewy.com
Requires-Python: >=3.10,<4.0
Classifier: Programming Language :: Python :: 3
Classifier: Programming Language :: Python :: 3.10
Classifier: Programming Language :: Python :: 3.11
